{
  "$schema": "https://json-schema.org/draft/2020-12/schema",
  "$id": "antirot/manifest.schema.json",
  "title": "antirot build manifest",
  "description": "The frozen coordination layer for a course build. Authored in the design phase, approved at the gate, consumed deterministically by build-artifacts.mjs and check.mjs, and passed to the build-course workflow as args. Controls names/order/structure ONLY — it is not the correctness guarantor.",
  "type": "object",
  "required": ["course", "concepts", "notes", "edges", "modules"],
  "additionalProperties": false,
  "properties": {
    "course": {
      "type": "object",
      "required": ["title", "slug", "outDir"],
      "additionalProperties": false,
      "properties": {
        "title": { "type": "string" },
        "slug": { "type": "string", "pattern": "^[a-z0-9-]+$" },
        "outDir": { "type": "string", "description": "Output directory for the vault, relative to cwd, e.g. ./Confluent-Parallel-Language-Theory" },
        "pacing": {
          "type": "object",
          "additionalProperties": false,
          "properties": {
            "density": { "enum": ["terse", "balanced", "gentle"] },
            "assumedBackground": { "type": "string" },
            "timeBudgetMin": { "type": "number", "description": "Target minutes per lesson" }
          }
        }
      }
    },
    "voice": {
      "type": "object",
      "description": "Pillar A: the frozen voice contract every lesson-writer must imitate.",
      "required": ["register", "person", "exemplar"],
      "additionalProperties": false,
      "properties": {
        "register": { "type": "string", "description": "e.g. 'precise, direct, no validation-forward filler'" },
        "person": { "enum": ["first", "second", "third"] },
        "exemplar": { "type": "string", "description": "1-2 paragraph sample passage. Few-shot anchor; writers imitate this, not an adjective list." }
      }
    },
    "notation": {
      "type": "array",
      "description": "Pillar A: canonical symbol per recurring object. check.mjs flags divergence.",
      "items": {
        "type": "object",
        "required": ["object", "symbol"],
        "additionalProperties": false,
        "properties": {
          "object": { "type": "string", "description": "Human name of the mathematical/technical object, e.g. 'gradient of f'" },
          "symbol": { "type": "string", "description": "Canonical LaTeX, e.g. '\\\\nabla f'" },
          "firstNote": { "type": "string", "description": "slug of the note that introduces it" }
        }
      }
    },
    "concepts": {
      "type": "array",
      "items": {
        "type": "object",
        "required": ["id", "title", "homeNote"],
        "additionalProperties": false,
        "properties": {
          "id": { "type": "string", "pattern": "^[a-z0-9-]+$", "description": "Stable concept id; also the wikilink slug for its home note." },
          "title": { "type": "string" },
          "homeNote": { "type": "string", "description": "slug of the note where this concept is canonically defined (the unique `define` site)." },
          "difficulty": { "enum": ["intro", "applied", "theory", "proof"] },
          "criticality": { "enum": ["normal", "critical"], "description": "critical => routed to the stronger model and to claim-level review. Downstream lessons depend on its correctness." },
          "glossary": { "type": "boolean", "description": "Appears in the auto-generated Glossary index, which transcludes this concept's canonical definition (^def-<id>) from its home lesson. No separate definition is authored." },
          "groundingRequired": { "type": "boolean", "description": "If true, the generation workflow runs a researcher to attach real sources before this concept is written/reviewed. Set for niche, cutting-edge, low-confidence, or correctness-critical concepts the model may not reliably know." },
          "sources": {
            "type": "array",
            "description": "Real, fetched authoritative references for this concept (populated by the researcher pass, not recalled from memory). Shared by lesson-writer (grounding + citation) and course-reviewer (verification); the Resources appendix is built from these.",
            "items": {
              "type": "object",
              "required": ["title", "url"],
              "additionalProperties": false,
              "properties": {
                "title": { "type": "string" },
                "url": { "type": "string", "description": "Canonical URL, actually fetched." },
                "kind": { "enum": ["paper", "book", "docs", "reference", "tutorial", "other"] },
                "note": { "type": "string", "description": "One line on what this source establishes or where to read for depth." }
              }
            }
          }
        }
      }
    },
    "notes": {
      "type": "array",
      "items": {
        "type": "object",
        "required": ["slug", "path", "title", "module", "order", "beats", "linkVocab"],
        "additionalProperties": false,
        "properties": {
          "slug": { "type": "string", "pattern": "^[a-z0-9-]+$" },
          "path": { "type": "string", "description": "Path within outDir, e.g. '02-Reduction/03-beta-reduction.md'" },
          "title": { "type": "string" },
          "module": { "type": "string", "description": "module slug" },
          "order": { "type": "integer", "description": "Global topological index. A `use` link's target must have a strictly lower order." },
          "beats": {
            "type": "array",
            "description": "Pillar/pedagogy: the ordered concepts this note covers. A writer may ONLY `define` concepts listed here with kind=define.",
            "items": {
              "type": "object",
              "required": ["concept", "kind"],
              "additionalProperties": false,
              "properties": {
                "concept": { "type": "string", "description": "concept id" },
                "kind": { "enum": ["define", "use", "preview"] }
              }
            }
          },
          "linkVocab": {
            "type": "array",
            "items": { "type": "string" },
            "description": "Closed vocabulary: the ONLY concept ids this note may [[link]] to (its beats + prereqs + glossary). Out-of-vocab links are build failures."
          },
          "prereqs": { "type": "array", "items": { "type": "string" }, "description": "concept ids the reader must already know" },
          "alreadyTaught": { "type": "array", "items": { "type": "string" }, "description": "prereq concept ids the reader has SEEN in an earlier note: link, do not re-teach." },
          "blockIds": { "type": "array", "items": { "type": "string" }, "description": "Declared block ids this note defines, e.g. ['^def-confluence']. Transclusion targets must resolve to one of these." },
          "exercises": {
            "type": "array",
            "description": "Planned understanding-checks for this lesson, beyond the per-beat quick checks. Each is rendered as a foldable question + a verified foldable solution. Makes exercises checkable (coverage + solution-present) instead of ad-hoc.",
            "items": {
              "type": "object",
              "required": ["concept", "kind"],
              "additionalProperties": false,
              "properties": {
                "concept": { "type": "string", "description": "primary concept tested; must be in this note's linkVocab" },
                "kind": { "enum": ["recall", "apply", "derive", "prove"], "description": "cognitive level — prefer apply/derive over recall; recall is the per-beat quick check's job" },
                "interleave": { "type": "array", "items": { "type": "string" }, "description": "optional already-taught concept ids this exercise also draws on (spaced retrieval). Must be lower-order concepts." }
              }
            }
          },
          "figures": {
            "type": "array",
            "description": "Planned combinatorial-graph figures for this lesson, rendered to SVG by build-figures.mjs from a writer-authored spec. Each slot is checkable: spec present + valid + SVG rendered + embedded. KaTeX/LaTeX cannot draw graphs — use this (or mermaid for simple ones).",
            "items": {
              "type": "object",
              "required": ["id", "kind"],
              "additionalProperties": false,
              "properties": {
                "id": { "type": "string", "pattern": "^[a-z0-9-]+$", "description": "globally-unique figure id; spec at .antirot/figures/<id>.json, renders to assets/<id>.svg" },
                "kind": { "enum": ["graph", "digraph", "interaction-net"] },
                "caption": { "type": "string" }
              }
            }
          }
        }
      }
    },
    "edges": {
      "type": "array",
      "description": "Prereq DAG edges. from depends on to (to must be taught first).",
      "items": {
        "type": "object",
        "required": ["from", "to", "confidence"],
        "additionalProperties": false,
        "properties": {
          "from": { "type": "string", "description": "concept id that depends" },
          "to": { "type": "string", "description": "concept id that is the prerequisite" },
          "confidence": { "type": "number", "minimum": 0, "maximum": 1, "description": "Architect's calibrated confidence. The gate reviews lowest-confidence edges first." },
          "why": { "type": "string", "description": "One-line justification, e.g. 'beta-reduction uses substitution in its definition'." }
        }
      }
    },
    "modules": {
      "type": "array",
      "items": {
        "type": "object",
        "required": ["slug", "title", "order"],
        "additionalProperties": false,
        "properties": {
          "slug": { "type": "string", "pattern": "^[a-z0-9-]+$" },
          "title": { "type": "string" },
          "order": { "type": "integer" },
          "capstone": {
            "type": "object",
            "description": "Optional end-of-module integrative exercise that ties several concepts together. Rendered on the module overview with a foldable solution.",
            "additionalProperties": false,
            "properties": {
              "concepts": { "type": "array", "items": { "type": "string" }, "description": "concept ids the capstone integrates" },
              "prompt": { "type": "string", "description": "optional seed for the capstone task" }
            }
          }
        }
      }
    }
  }
}
